{
  "utterance": "Place each box on pallets and shelves with no stacking",
  "camera_intrinsics": [
    [
      305.4163695204686,
      0.0,
      320.0,
      0.0
    ],
    [
      0.0,
      305.41637878692075,
      240.0,
      0.0
    ],
    [
      0.0,
      0.0,
      1.0,
      0.0
    ],
    [
      0.0,
      0.0,
      0.0,
      1.0
    ]
  ],
  "all_classes": {
    "1": "floor",
    "2": "box",
    "3": "pallet",
    "4": "cell",
    "5": "shelf",
    "6": "distractor"
  },
  "target_id": [
    2,
    4
  ],
  "target_instances": [
    2005,
    4008
  ],
  "current_env_relationships": {
    "pallets": {
      "p0": {
        "id": "p0",
        "prim_path": "/World/p0",
        "capacity": 6,
        "top_z": 0.05,
        "center_xy": [
          4.72,
          0.77
        ],
        "instance_id": 3000,
        "yaw_deg": 90.0
      },
      "p1": {
        "id": "p1",
        "prim_path": "/World/p1",
        "capacity": 6,
        "top_z": 0.05,
        "center_xy": [
          1.72,
          1.04
        ],
        "instance_id": 3001,
        "yaw_deg": 90.0
      },
      "p2": {
        "id": "p2",
        "prim_path": "/World/p2",
        "capacity": 4,
        "top_z": 0.05,
        "center_xy": [
          3.05,
          3.41
        ],
        "instance_id": 3002,
        "yaw_deg": 90.0
      }
    },
    "boxes": {
      "box_0": {
        "id": "box_0",
        "prim_path": "/World/box_0",
        "size_xyz": [
          1.0,
          1.0,
          1.0
        ],
        "instance_id": 2000,
        "center_xy": [
          1.72,
          0.79
        ],
        "color": "red",
        "top_z": 1.6800000000000002,
        "occupied": false,
        "on_top_of": "p1_r2_c0",
        "under_box": null,
        "pallet_id": "p1",
        "cell_id": "p1_r2_c0",
        "yaw_deg": 90.0
      },
      "box_1": {
        "id": "box_1",
        "prim_path": "/World/box_1",
        "size_xyz": [
          1.0,
          1.0,
          1.0
        ],
        "instance_id": 2001,
        "center_xy": [
          -4.96,
          -0.4
        ],
        "color": "blue",
        "top_z": 1.05,
        "occupied": false,
        "on_top_of": null,
        "under_box": null,
        "pallet_id": null,
        "cell_id": null,
        "yaw_deg": 0.0
      },
      "box_2": {
        "id": "box_2",
        "prim_path": "/World/box_2",
        "size_xyz": [
          1.0,
          1.0,
          1.0
        ],
        "instance_id": 2002,
        "center_xy": [
          -5.08,
          0.88
        ],
        "color": "yellow",
        "top_z": 1.05,
        "occupied": false,
        "on_top_of": null,
        "under_box": null,
        "pallet_id": null,
        "cell_id": null,
        "yaw_deg": 0.0
      },
      "box_3": {
        "id": "box_3",
        "prim_path": "/World/box_3",
        "size_xyz": [
          1.0,
          1.0,
          1.0
        ],
        "instance_id": 2003,
        "center_xy": [
          -3.97,
          0.47
        ],
        "color": "red",
        "top_z": 1.05,
        "occupied": false,
        "on_top_of": null,
        "under_box": null,
        "pallet_id": null,
        "cell_id": null,
        "yaw_deg": 0.0
      },
      "box_4": {
        "id": "box_4",
        "prim_path": "/World/box_4",
        "size_xyz": [
          1.0,
          1.0,
          1.0
        ],
        "instance_id": 2004,
        "center_xy": [
          -3.95,
          3.18
        ],
        "color": "blue",
        "top_z": 1.05,
        "occupied": false,
        "on_top_of": null,
        "under_box": null,
        "pallet_id": null,
        "cell_id": null,
        "yaw_deg": 0.0
      },
      "box_5": {
        "id": "box_5",
        "prim_path": "/World/box_5",
        "size_xyz": [
          1.0,
          1.0,
          1.0
        ],
        "instance_id": 2005,
        "center_xy": [
          -2.39,
          3.76
        ],
        "color": "yellow",
        "top_z": 1.05,
        "occupied": false,
        "on_top_of": null,
        "under_box": null,
        "pallet_id": null,
        "cell_id": null,
        "yaw_deg": 0.0
      },
      "box_6": {
        "id": "box_6",
        "prim_path": "/World/box_6",
        "size_xyz": [
          1.0,
          1.0,
          1.0
        ],
        "instance_id": 2006,
        "center_xy": [
          1.72,
          1.29
        ],
        "color": "blue",
        "top_z": 1.6800000000000002,
        "occupied": false,
        "on_top_of": "p1_r2_c1",
        "under_box": null,
        "pallet_id": "p1",
        "cell_id": "p1_r2_c1",
        "yaw_deg": 90.0
      },
      "box_7": {
        "id": "box_7",
        "prim_path": "/World/box_7",
        "size_xyz": [
          1.0,
          1.0,
          1.0
        ],
        "instance_id": 2007,
        "center_xy": [
          -3.61,
          1.12
        ],
        "color": "red",
        "top_z": 1.05,
        "occupied": false,
        "on_top_of": null,
        "under_box": null,
        "pallet_id": null,
        "cell_id": null,
        "yaw_deg": 0.0
      },
      "box_8": {
        "id": "box_8",
        "prim_path": "/World/box_8",
        "size_xyz": [
          1.0,
          1.0,
          1.0
        ],
        "instance_id": 2008,
        "center_xy": [
          -1.46,
          -3.81
        ],
        "color": "blue",
        "top_z": 1.05,
        "occupied": false,
        "on_top_of": null,
        "under_box": null,
        "pallet_id": null,
        "cell_id": null,
        "yaw_deg": 0.0
      },
      "box_9": {
        "id": "box_9",
        "prim_path": "/World/box_9",
        "size_xyz": [
          1.0,
          1.0,
          1.0
        ],
        "instance_id": 2009,
        "center_xy": [
          -3.66,
          -2.05
        ],
        "color": "yellow",
        "top_z": 1.05,
        "occupied": false,
        "on_top_of": null,
        "under_box": null,
        "pallet_id": null,
        "cell_id": null,
        "yaw_deg": 0.0
      },
      "box_10": {
        "id": "box_10",
        "prim_path": "/World/box_10",
        "size_xyz": [
          1.0,
          1.0,
          1.0
        ],
        "instance_id": 2010,
        "center_xy": [
          -3.83,
          1.42
        ],
        "color": "red",
        "top_z": 1.05,
        "occupied": false,
        "on_top_of": null,
        "under_box": null,
        "pallet_id": null,
        "cell_id": null,
        "yaw_deg": 0.0
      },
      "box_11": {
        "id": "box_11",
        "prim_path": "/World/box_11",
        "size_xyz": [
          1.0,
          1.0,
          1.0
        ],
        "instance_id": 2011,
        "center_xy": [
          -3.37,
          2.64
        ],
        "color": "blue",
        "top_z": 1.05,
        "occupied": false,
        "on_top_of": null,
        "under_box": null,
        "pallet_id": null,
        "cell_id": null,
        "yaw_deg": 0.0
      },
      "box_12": {
        "id": "box_12",
        "prim_path": "/World/box_12",
        "size_xyz": [
          1.0,
          1.0,
          1.0
        ],
        "instance_id": 2012,
        "center_xy": [
          -3.64,
          -1.47
        ],
        "color": "blue",
        "top_z": 1.05,
        "occupied": false,
        "on_top_of": null,
        "under_box": null,
        "pallet_id": null,
        "cell_id": null,
        "yaw_deg": 0.0
      },
      "box_13": {
        "id": "box_13",
        "prim_path": "/World/box_13",
        "size_xyz": [
          1.0,
          1.0,
          1.0
        ],
        "instance_id": 2013,
        "center_xy": [
          1.2,
          0.79
        ],
        "color": "yellow",
        "top_z": 1.6800000000000002,
        "occupied": false,
        "on_top_of": "p1_r0_c1",
        "under_box": null,
        "pallet_id": "p1",
        "cell_id": "p1_r0_c1",
        "yaw_deg": 90.0
      },
      "box_14": {
        "id": "box_14",
        "prim_path": "/World/box_14",
        "size_xyz": [
          1.0,
          1.0,
          1.0
        ],
        "instance_id": 2014,
        "center_xy": [
          1.2,
          1.29
        ],
        "color": "red",
        "top_z": 1.6800000000000002,
        "occupied": false,
        "on_top_of": "p1_r0_c0",
        "under_box": null,
        "pallet_id": "p1",
        "cell_id": "p1_r0_c0",
        "yaw_deg": 90.0
      },
      "box_15": {
        "id": "box_15",
        "prim_path": "/World/box_15",
        "size_xyz": [
          1.0,
          1.0,
          1.0
        ],
        "instance_id": 2015,
        "center_xy": [
          -2.95,
          2.95
        ],
        "color": "blue",
        "top_z": 1.05,
        "occupied": false,
        "on_top_of": null,
        "under_box": null,
        "pallet_id": null,
        "cell_id": null,
        "yaw_deg": 0.0
      }
    },
    "cells": {
      "p0_r0_c0": {
        "id": "p0_r0_c0",
        "pallet_id": "p0",
        "yaw_deg": 90.0,
        "instance_id": 4000,
        "center_xy": [
          4.2,
          1.02
        ],
        "box_id": null,
        "prim_path": "/World/p0/pallet_a1/c1",
        "stack_height": 0,
        "occupied": false,
        "max_stack": 5
      },
      "p0_r0_c1": {
        "id": "p0_r0_c1",
        "pallet_id": "p0",
        "yaw_deg": 90.0,
        "instance_id": 4001,
        "center_xy": [
          4.2,
          0.52
        ],
        "box_id": null,
        "prim_path": "/World/p0/pallet_a1/c2",
        "stack_height": 0,
        "occupied": false,
        "max_stack": 5
      },
      "p0_r1_c0": {
        "id": "p0_r1_c0",
        "pallet_id": "p0",
        "yaw_deg": 90.0,
        "instance_id": 4002,
        "center_xy": [
          5.24,
          0.52
        ],
        "box_id": null,
        "prim_path": "/World/p0/pallet_a1/c3",
        "stack_height": 0,
        "occupied": false,
        "max_stack": 5
      },
      "p0_r1_c1": {
        "id": "p0_r1_c1",
        "pallet_id": "p0",
        "yaw_deg": 90.0,
        "instance_id": 4003,
        "center_xy": [
          5.24,
          1.02
        ],
        "box_id": null,
        "prim_path": "/World/p0/pallet_a1/c4",
        "stack_height": 0,
        "occupied": false,
        "max_stack": 5
      },
      "p0_r2_c0": {
        "id": "p0_r2_c0",
        "pallet_id": "p0",
        "yaw_deg": 90.0,
        "instance_id": 4004,
        "center_xy": [
          4.72,
          0.52
        ],
        "box_id": null,
        "prim_path": "/World/p0/pallet_a1/c5",
        "stack_height": 0,
        "occupied": false,
        "max_stack": 5
      },
      "p0_r2_c1": {
        "id": "p0_r2_c1",
        "pallet_id": "p0",
        "yaw_deg": 90.0,
        "instance_id": 4005,
        "center_xy": [
          4.72,
          1.02
        ],
        "box_id": null,
        "prim_path": "/World/p0/pallet_a1/c6",
        "stack_height": 0,
        "occupied": false,
        "max_stack": 5
      },
      "p1_r0_c0": {
        "id": "p1_r0_c0",
        "pallet_id": "p1",
        "yaw_deg": 90.0,
        "instance_id": 4004,
        "center_xy": [
          1.2,
          1.29
        ],
        "box_id": "box_14",
        "prim_path": "/World/p1/pallet_a1/c1",
        "stack_height": 1,
        "occupied": true,
        "max_stack": 5
      },
      "p1_r0_c1": {
        "id": "p1_r0_c1",
        "pallet_id": "p1",
        "yaw_deg": 90.0,
        "instance_id": 4005,
        "center_xy": [
          1.2,
          0.79
        ],
        "box_id": "box_13",
        "prim_path": "/World/p1/pallet_a1/c2",
        "stack_height": 1,
        "occupied": true,
        "max_stack": 5
      },
      "p1_r1_c0": {
        "id": "p1_r1_c0",
        "pallet_id": "p1",
        "yaw_deg": 90.0,
        "instance_id": 4006,
        "center_xy": [
          2.24,
          0.79
        ],
        "box_id": null,
        "prim_path": "/World/p1/pallet_a1/c3",
        "stack_height": 0,
        "occupied": false,
        "max_stack": 5
      },
      "p1_r1_c1": {
        "id": "p1_r1_c1",
        "pallet_id": "p1",
        "yaw_deg": 90.0,
        "instance_id": 4007,
        "center_xy": [
          2.24,
          1.29
        ],
        "box_id": null,
        "prim_path": "/World/p1/pallet_a1/c4",
        "stack_height": 0,
        "occupied": false,
        "max_stack": 5
      },
      "p1_r2_c0": {
        "id": "p1_r2_c0",
        "pallet_id": "p1",
        "yaw_deg": 90.0,
        "instance_id": 4008,
        "center_xy": [
          1.72,
          0.79
        ],
        "box_id": "box_0",
        "prim_path": "/World/p1/pallet_a1/c5",
        "stack_height": 1,
        "occupied": true,
        "max_stack": 5
      },
      "p1_r2_c1": {
        "id": "p1_r2_c1",
        "pallet_id": "p1",
        "yaw_deg": 90.0,
        "instance_id": 4009,
        "center_xy": [
          1.72,
          1.29
        ],
        "box_id": "box_6",
        "prim_path": "/World/p1/pallet_a1/c6",
        "stack_height": 1,
        "occupied": true,
        "max_stack": 5
      },
      "p2_r0_c0": {
        "id": "p2_r0_c0",
        "pallet_id": "p2",
        "yaw_deg": 90.0,
        "instance_id": 4008,
        "center_xy": [
          2.79,
          3.66
        ],
        "box_id": null,
        "prim_path": "/World/p2/pallet_a1/c1",
        "stack_height": 0,
        "occupied": false,
        "max_stack": 5
      },
      "p2_r0_c1": {
        "id": "p2_r0_c1",
        "pallet_id": "p2",
        "yaw_deg": 90.0,
        "instance_id": 4009,
        "center_xy": [
          2.79,
          3.16
        ],
        "box_id": null,
        "prim_path": "/World/p2/pallet_a1/c2",
        "stack_height": 0,
        "occupied": false,
        "max_stack": 5
      },
      "p2_r1_c0": {
        "id": "p2_r1_c0",
        "pallet_id": "p2",
        "yaw_deg": 90.0,
        "instance_id": 4010,
        "center_xy": [
          3.31,
          3.16
        ],
        "box_id": null,
        "prim_path": "/World/p2/pallet_a1/c3",
        "stack_height": 0,
        "occupied": false,
        "max_stack": 5
      },
      "p2_r1_c1": {
        "id": "p2_r1_c1",
        "pallet_id": "p2",
        "yaw_deg": 90.0,
        "instance_id": 4011,
        "center_xy": [
          3.31,
          3.66
        ],
        "box_id": null,
        "prim_path": "/World/p2/pallet_a1/c4",
        "stack_height": 0,
        "occupied": false,
        "max_stack": 5
      },
      "s0_r0_c0": {
        "id": "s0_r0_c0",
        "pallet_id": "s0",
        "yaw_deg": 90.0,
        "instance_id": 4016,
        "center_xy": [
          5.26,
          -2.27
        ],
        "box_id": null,
        "prim_path": "/World/s0/Shelf_1/c1",
        "stack_height": 0,
        "occupied": false,
        "max_stack": 1
      },
      "s0_r0_c1": {
        "id": "s0_r0_c1",
        "pallet_id": "s0",
        "yaw_deg": 90.0,
        "instance_id": 4017,
        "center_xy": [
          4.71,
          -2.27
        ],
        "box_id": null,
        "prim_path": "/World/s0/Shelf_1/c2",
        "stack_height": 0,
        "occupied": false,
        "max_stack": 1
      },
      "s0_r0_c2": {
        "id": "s0_r0_c2",
        "pallet_id": "s0",
        "yaw_deg": 90.0,
        "instance_id": 4018,
        "center_xy": [
          5.26,
          -2.27
        ],
        "box_id": null,
        "prim_path": "/World/s0/Shelf_1/c3",
        "stack_height": 0,
        "occupied": false,
        "max_stack": 1
      },
      "s0_r1_c0": {
        "id": "s0_r1_c0",
        "pallet_id": "s0",
        "yaw_deg": 90.0,
        "instance_id": 4019,
        "center_xy": [
          4.71,
          -2.27
        ],
        "box_id": null,
        "prim_path": "/World/s0/Shelf_1/c4",
        "stack_height": 0,
        "occupied": false,
        "max_stack": 1
      }
    },
    "shelfs": {
      "s0": {
        "id": "s0",
        "prim_path": "/World/s0",
        "capacity": 4,
        "top_z": 0.05,
        "center_xy": [
          4.98,
          -2.27
        ],
        "instance_id": 5000,
        "yaw_deg": 90.0
      }
    },
    "props": {
      "prop_0": {
        "id": "prop_0",
        "prim_path": "/World/prop_0",
        "center_xy": [
          -3.847831305479322,
          -1.9622578297772413
        ],
        "instance_id": 6000
      },
      "prop_1": {
        "id": "prop_1",
        "prim_path": "/World/prop_1",
        "center_xy": [
          -0.8261528268881277,
          3.809383571086425
        ],
        "instance_id": 6001
      },
      "prop_2": {
        "id": "prop_2",
        "prim_path": "/World/prop_2",
        "center_xy": [
          -2.9497011014522005,
          1.0042409612691632
        ],
        "instance_id": 6002
      }
    }
  }
}
